{
  "version": "3.0.0",
  "terminal_id": "1223fbc66993",
  "timestamp": "2026-04-17T16:20:31.222046",
  "session_id": "2026-04-17T16:20:31.184884",
  "gaps": [],
  "metadata": {
    "timestamp": "2026-04-17T16:20:31.184884",
    "project_root": "P:\\packages\\handoff",
    "terminal_id": "1223fbc66993",
    "viability_check": {
      "is_viable": true,
      "failure_reason": null
    },
    "git_context": {
      "branch": "main",
      "branch_display": "main",
      "is_detached": false,
      "is_worktree": false,
      "worktree_count": 1,
      "error": null
    },
    "subagent_results": {},
    "resolution_result": {
      "resolved_count": 0,
      "new_count": 0,
      "credited_skill": null
    }
  }
}